capiscio_sdk/__init__.py
capiscio_sdk/badge.py
capiscio_sdk/badge_keeper.py
capiscio_sdk/config.py
capiscio_sdk/dv.py
capiscio_sdk/errors.py
capiscio_sdk/executor.py
capiscio_sdk/py.typed
capiscio_sdk/simple_guard.py
capiscio_sdk/types.py
capiscio_sdk/_rpc/__init__.py
capiscio_sdk/_rpc/client.py
capiscio_sdk/_rpc/process.py
capiscio_sdk/_rpc/gen/__init__.py
capiscio_sdk/infrastructure/__init__.py
capiscio_sdk/infrastructure/cache.py
capiscio_sdk/infrastructure/rate_limiter.py
capiscio_sdk/integrations/fastapi.py
capiscio_sdk/scoring/__init__.py
capiscio_sdk/scoring/availability.py
capiscio_sdk/scoring/compliance.py
capiscio_sdk/scoring/trust.py
capiscio_sdk/scoring/types.py
capiscio_sdk/validators/__init__.py
capiscio_sdk/validators/_core.py
capiscio_sdk/validators/agent_card.py
capiscio_sdk/validators/certificate.py
capiscio_sdk/validators/message.py
capiscio_sdk/validators/protocol.py
capiscio_sdk/validators/semver.py
capiscio_sdk/validators/signature.py
capiscio_sdk/validators/url_security.py
capiscio_sdk-2.3.1.dist-info/METADATA
capiscio_sdk-2.3.1.dist-info/WHEEL
capiscio_sdk-2.3.1.dist-info/licenses/LICENSE
capiscio_sdk-2.3.1.dist-info/RECORD
