Metadata-Version: 2.4
Name: capiscio-sdk
Version: 2.3.1
Summary: Runtime security middleware for A2A agents
Project-URL: Homepage, https://capisc.io
Project-URL: Documentation, https://docs.capisc.io/sdk-python
Project-URL: Repository, https://github.com/capiscio/capiscio-sdk-python
Project-URL: Issues, https://github.com/capiscio/capiscio-sdk-python/issues
Author-email: Capiscio Team <team@capisc.io>
License: Apache-2.0
License-File: LICENSE
Keywords: a2a,agent,agent-to-agent,middleware,security,validation
Classifier: Development Status :: 3 - Alpha
Classifier: Intended Audience :: Developers
Classifier: License :: OSI Approved :: Apache Software License
Classifier: Programming Language :: Python :: 3
Classifier: Programming Language :: Python :: 3.10
Classifier: Programming Language :: Python :: 3.11
Classifier: Programming Language :: Python :: 3.12
Classifier: Programming Language :: Python :: 3.13
Classifier: Topic :: Security
Classifier: Topic :: Software Development :: Libraries :: Python Modules
Requires-Python: >=3.10
Requires-Dist: a2a-sdk>=0.1.0
Requires-Dist: cachetools>=5.3.0
Requires-Dist: cryptography>=42.0.0
Requires-Dist: grpcio>=1.60.0
Requires-Dist: httpx>=0.27.0
Requires-Dist: protobuf>=4.25.0
Requires-Dist: pydantic>=2.0.0
Requires-Dist: pyjwt[crypto]>=2.8.0
Provides-Extra: dev
Requires-Dist: black>=24.0.0; extra == 'dev'
Requires-Dist: fastapi>=0.100.0; extra == 'dev'
Requires-Dist: mypy>=1.9.0; extra == 'dev'
Requires-Dist: pytest-asyncio>=0.23.0; extra == 'dev'
Requires-Dist: pytest-cov>=4.1.0; extra == 'dev'
Requires-Dist: pytest>=8.0.0; extra == 'dev'
Requires-Dist: ruff>=0.3.0; extra == 'dev'
Requires-Dist: starlette>=0.27.0; extra == 'dev'
Requires-Dist: types-cachetools>=5.3.0; extra == 'dev'
Provides-Extra: web
Requires-Dist: fastapi>=0.100.0; extra == 'web'
Requires-Dist: starlette>=0.27.0; extra == 'web'
